examples/fastapi_example.py
memhunt/__init__.py
memhunt/tests.py
memhunt/browser/__init__.py
memhunt/browser/views.py
objgraph/browser/views.py
tests/__init__.py
tests/conftest.py
tests/test_views.py
memhunt-0.0.1.dist-info/METADATA
memhunt-0.0.1.dist-info/WHEEL
memhunt-0.0.1.dist-info/top_level.txt
memhunt-0.0.1.dist-info/RECORD
