Metadata-Version: 2.4
Name: memhunt
Version: 0.0.1
Summary: Memory debugging tools for Python applications
Author: Holmes Corporation
Author-email: Daniel Blackburn <danielb@holmescorp.com>
Maintainer-email: Daniel Blackburn <danielb@holmescorp.com>
License: ZPL 2.1
Project-URL: Homepage, https://github.com/blackburnd/memhunt
Project-URL: Repository, https://github.com/blackburnd/memhunt.git
Project-URL: Issues, https://github.com/blackburnd/memhunt/issues
Keywords: memory,objgraph,graphviz,pympler,debugging,profiling
Classifier: Development Status :: 4 - Beta
Classifier: Environment :: Web Environment
Classifier: Intended Audience :: Developers
Classifier: License :: OSI Approved :: Zope Public License
Classifier: Programming Language :: Python
Classifier: Programming Language :: Python :: 3
Classifier: Programming Language :: Python :: 3.8
Classifier: Programming Language :: Python :: 3.9
Classifier: Programming Language :: Python :: 3.10
Classifier: Programming Language :: Python :: 3.11
Classifier: Programming Language :: Python :: 3.12
Classifier: Natural Language :: English
Classifier: Operating System :: OS Independent
Classifier: Topic :: Internet :: WWW/HTTP
Classifier: Topic :: Software Development :: Debuggers
Classifier: Topic :: System :: Monitoring
Requires-Python: >=3.8
Requires-Dist: setuptools
Requires-Dist: pympler>=0.9
Requires-Dist: objgraph>=3.5.0
Requires-Dist: jinja2>=3.0.0
Provides-Extra: test
Requires-Dist: pytest>=6.0; extra == "test"
Requires-Dist: pytest-cov>=2.10; extra == "test"
Requires-Dist: pytest-mock>=3.0; extra == "test"
Requires-Dist: coverage[toml]>=5.0; extra == "test"
Provides-Extra: fastapi
Requires-Dist: fastapi>=0.68.0; extra == "fastapi"
Requires-Dist: uvicorn>=0.15.0; extra == "fastapi"
Provides-Extra: dev
Requires-Dist: z3c.memhunt.objgraph[test]; extra == "dev"
Requires-Dist: black>=22.0; extra == "dev"
Requires-Dist: flake8>=4.0; extra == "dev"
Requires-Dist: mypy>=0.910; extra == "dev"
Requires-Dist: pre-commit>=2.15; extra == "dev"
Requires-Dist: tox>=3.24; extra == "dev"
Dynamic: requires-python
